flaskriver/ClassificationInterface.py
flaskriver/Interface.py
flaskriver/RegressionInterface.py
flaskriver/__init__.py
flaskriver-0.0.4.dist-info/LICENSE
flaskriver-0.0.4.dist-info/WHEEL
flaskriver-0.0.4.dist-info/METADATA
flaskriver-0.0.4.dist-info/RECORD
