Metadata-Version: 2.1
Name: flaskriver
Version: 0.0.4
Summary: This is a package which aims to combine the lighweight web-framework flask
Author-email: Sebastian Wette  <mail@sebastianwette.de>
Classifier: License :: OSI Approved :: MIT License
Requires-Dist: flask
Project-URL: Home, https://github.com/sebiwtt/flaskriver
